{
	"id": "enchanter_compel",
	"status": "wip",
	"name": "Compel",
	"school": "Enchanter",
	"rarity": "Common",
	"top": {
		"name": "Compel",
		"mana": 1,
		"speed": "Instant",
		"rules_text": "Pull an enemy 2 tiles toward you. If it lands on one of your glyphs, trigger it.",
		"tags": [
			"enchantment",
			"charm"
		],
		"targeting": {
			"type": "unit",
			"range": 6,
			"los": false,
			"enemies_only": true
		},
		"effect": {
			"type": "pull_to_glyph",
			"tiles": 2
		}
	},
	"bottom": {
		"name": "Sigil of Focus",
		"mana": 1,
		"speed": "Sorcery",
		"rules_text": "Prepare a glyph within 4. While you stand on it, your spells cost 1 less. Draw 1 card.",
		"tags": [
			"enchantment",
			"glyph"
		],
		"targeting": {
			"type": "tile",
			"range": 4
		},
		"effect": {
			"type": "sequence",
			"steps": [
				{
					"type": "prepare_glyph",
					"trigger": "self_stand",
					"caster_cost_reduction": 1,
					"duration": 3,
					"reusable": true
				},
				{
					"type": "draw",
					"count": 1
				}
			]
		}
	},
	"upgrades": [
		{
			"tier": 1,
			"half": "both",
			"top_name": "Compel+",
			"bottom_name": "Sigil of Focus+",
			"description": "Pull harder. The focus sigil lasts longer.",
			"changes": [
				{
					"half": "top",
					"field": "effect.tiles",
					"value": 3
				},
				{
					"half": "top",
					"field": "rules_text",
					"value": "Pull an enemy 3 tiles toward you. If it lands on a glyph, trigger it."
				},
				{
					"half": "bottom",
					"field": "effect.steps[0].duration",
					"value": 4
				},
				{
					"half": "bottom",
					"field": "rules_text",
					"value": "Prepare a glyph within 4. While you stand on it, your spells cost 1 less (4 turns). Draw 1 card."
				}
			]
		},
		{
			"tier": 2,
			"half": "top",
			"top_name": "Dominate Step",
			"description": "Dominate Step: collisions deal damage.",
			"changes": [
				{
					"half": "top",
					"field": "effect.collision_damage",
					"value": 5
				},
				{
					"half": "top",
					"field": "rules_text",
					"value": "Pull an enemy 3 tiles toward you. Collision deals 5. Glyph landings trigger."
				}
			]
		},
		{
			"tier": 2,
			"half": "bottom",
			"bottom_name": "Sigil of Power",
			"description": "Sigil of Power: also grants +2 damage while you stand on it.",
			"changes": [
				{
					"half": "bottom",
					"field": "effect.steps[0].caster_damage",
					"value": 2
				},
				{
					"half": "bottom",
					"field": "rules_text",
					"value": "Prepare a glyph within 4. While you stand on it, your spells cost 1 less and deal +2. Draw 1."
				}
			]
		},
		{
			"tier": 3,
			"half": "top",
			"top_name": "Mass Compel",
			"description": "Mass Compel: drag several enemies in.",
			"changes": [
				{
					"half": "top",
					"field": "effect",
					"value": {
						"type": "retarget",
						"targeting": {
							"type": "aoe",
							"radius": 2,
							"enemies_only": true
						},
						"do": {
							"type": "pull_to_glyph",
							"tiles": 3,
							"collision_damage": 5
						}
					}
				},
				{
					"half": "top",
					"field": "targeting",
					"value": {
						"type": "tile",
						"range": 6
					}
				},
				{
					"half": "top",
					"field": "rules_text",
					"value": "Pull all enemies within 2 of the target 3 tiles toward you. Collisions deal 5; glyph landings trigger."
				}
			]
		},
		{
			"tier": 3,
			"half": "bottom",
			"bottom_name": "Throne Sigil",
			"description": "Throne Sigil: also banks Weave each turn you hold it.",
			"changes": [
				{
					"half": "bottom",
					"field": "effect.steps[0].caster_weave_per_turn",
					"value": 1
				},
				{
					"half": "bottom",
					"field": "rules_text",
					"value": "Prepare a glyph within 4. While on it: spells cost 1 less, deal +2, and gain 1 Weave/turn. Draw 1."
				}
			]
		},
		{
			"tier": 4,
			"half": "top",
			"top_name": "Absolute Compulsion",
			"description": "Absolute Compulsion: drag them in and Name them.",
			"changes": [
				{
					"half": "top",
					"field": "effect",
					"value": {
						"type": "retarget",
						"targeting": {
							"type": "aoe",
							"radius": 2,
							"enemies_only": true
						},
						"do": {
							"type": "sequence",
							"steps": [
								{
									"type": "pull_to_glyph",
									"tiles": 3,
									"collision_damage": 6
								},
								{
									"type": "apply_status",
									"status": "named",
									"duration": 1
								}
							]
						}
					}
				},
				{
					"half": "top",
					"field": "targeting",
					"value": {
						"type": "tile",
						"range": 6
					}
				},
				{
					"half": "top",
					"field": "rules_text",
					"value": "Pull all enemies within 2 toward you (6 collision) and Name each for 1 turn."
				}
			]
		},
		{
			"tier": 4,
			"half": "bottom",
			"bottom_name": "Seat of Power",
			"description": "Seat of Power: the ultimate caster throne.",
			"changes": [
				{
					"half": "bottom",
					"field": "effect",
					"value": {
						"type": "sequence",
						"steps": [
							{
								"type": "prepare_glyph",
								"trigger": "self_stand",
								"caster_cost_reduction": 2,
								"caster_damage": 3,
								"caster_weave_per_turn": 1,
								"duration": 99,
								"reusable": true
							},
							{
								"type": "draw",
								"count": 2
							}
						]
					}
				},
				{
					"half": "bottom",
					"field": "rules_text",
					"value": "Prepare a permanent glyph within 4. While on it: spells cost 2 less, deal +3, gain 1 Weave/turn. Draw 2."
				}
			]
		}
	]
}